<?xml version="1.0" encoding="utf-8"?>
<clothing-items>
 <clothing>
  <id>
   453064617
  </id>
  <name>
   DC Gloves F-8902
  </name>
  <category>
   Gloves
  </category>
  <size>
   S
  </size>
  <color>
   Оранжевый
  </color>
  <material>
   Вискоза
  </material>
  <price>
   811670
  </price>
  <rating>
   4.48
  </rating>
  <reviews>
   982949
  </reviews>
 </clothing>
 <clothing>
  <id>
   568449585
  </id>
  <name>
   Under Armour Sweater Q-2265
  </name>
  <category>
   Sweater
  </category>
  <size>
   L
  </size>
  <color>
   Синий
  </color>
  <material>
   Хлопок
  </material>
  <price>
   817371
  </price>
  <rating>
   1.73
  </rating>
  <reviews>
   321183
  </reviews>
  <new>
   +
  </new>
  <sporty>
   no
  </sporty>
 </clothing>
 <clothing>
  <id>
   651631237
  </id>
  <name>
   Vans Gloves N-4249
  </name>
  <category>
   Gloves
  </category>
  <size>
   S
  </size>
  <color>
   Оранжевый
  </color>
  <material>
   Шерсть
  </material>
  <price>
   517858
  </price>
  <rating>
   2.86
  </rating>
  <reviews>
   957737
  </reviews>
  <new>
   -
  </new>
 </clothing>
 <clothing>
  <id>
   235710588
  </id>
  <name>
   Lacoste Jacket M-4414
  </name>
  <category>
   Jacket
  </category>
  <size>
   XL
  </size>
  <color>
   Синий
  </color>
  <material>
   Кожа
  </material>
  <price>
   190856
  </price>
  <rating>
   4.05
  </rating>
  <reviews>
   711801
  </reviews>
  <new>
   -
  </new>
  <exclusive>
   no
  </exclusive>
 </clothing>
 <clothing>
  <id>
   597655881
  </id>
  <name>
   Asics Socks H-3206
  </name>
  <category>
   Socks
  </category>
  <size>
   S
  </size>
  <color>
   Фиолетовый
  </color>
  <material>
   Вискоза
  </material>
  <price>
   354833
  </price>
  <rating>
   4.59
  </rating>
  <reviews>
   550720
  </reviews>
  <new>
   -
  </new>
  <sporty>
   no
  </sporty>
 </clothing>
 <clothing>
  <id>
   846812043
  </id>
  <name>
   Vans T-shirt M-5955
  </name>
  <category>
   T-shirt
  </category>
  <size>
   XL
  </size>
  <color>
   Зеленый
  </color>
  <material>
   Хлопок
  </material>
  <price>
   171581
  </price>
  <rating>
   1.29
  </rating>
  <reviews>
   767215
  </reviews>
  <new>
   +
  </new>
  <exclusive>
   no
  </exclusive>
  <sporty>
   yes
  </sporty>
 </clothing>
 <clothing>
  <id>
   492656074
  </id>
  <name>
   New Balance Handbags D-8944
  </name>
  <category>
   Handbags
  </category>
  <size>
   M
  </size>
  <color>
   Желтый
  </color>
  <material>
   Шелк
  </material>
  <price>
   870638
  </price>
  <rating>
   4.37
  </rating>
  <reviews>
   295762
  </reviews>
  <new>
   +
  </new>
  <sporty>
   no
  </sporty>
 </clothing>
 <clothing>
  <id>
   925799589
  </id>
  <name>
   Nike Socks K-2531
  </name>
  <category>
   Socks
  </category>
  <size>
   S
  </size>
  <color>
   Зеленый
  </color>
  <material>
   Нейлон
  </material>
  <price>
   343598
  </price>
  <rating>
   4.22
  </rating>
  <reviews>
   541317
  </reviews>
  <exclusive>
   yes
  </exclusive>
  <sporty>
   no
  </sporty>
 </clothing>
 <clothing>
  <id>
   675811039
  </id>
  <name>
   Adidas Handbags D-1143
  </name>
  <category>
   Handbags
  </category>
  <size>
   S
  </size>
  <color>
   Голубой
  </color>
  <material>
   Шерсть
  </material>
  <price>
   543579
  </price>
  <rating>
   2.02
  </rating>
  <reviews>
   769424
  </reviews>
  <new>
   -
  </new>
  <exclusive>
   no
  </exclusive>
  <sporty>
   no
  </sporty>
 </clothing>
 <clothing>
  <id>
   565206115
  </id>
  <name>
   Nike Pants T-6339
  </name>
  <category>
   Pants
  </category>
  <size>
   XL
  </size>
  <color>
   Оранжевый
  </color>
  <material>
   Нейлон
  </material>
  <price>
   151406
  </price>
  <rating>
   2.08
  </rating>
  <reviews>
   435091
  </reviews>
 </clothing>
 <clothing>
  <id>
   150790282
  </id>
  <name>
   DC Pants V-6889
  </name>
  <category>
   Pants
  </category>
  <size>
   XXL
  </size>
  <color>
   Желтый
  </color>
  <material>
   Шерсть
  </material>
  <price>
   673028
  </price>
  <rating>
   2.95
  </rating>
  <reviews>
   247082
  </reviews>
  <new>
   +
  </new>
  <sporty>
   yes
  </sporty>
 </clothing>
</clothing-items>
